imgopt/__init__.py
imgopt-0.3.dist-info/METADATA
imgopt-0.3.dist-info/WHEEL
imgopt-0.3.dist-info/top_level.txt
imgopt-0.3.dist-info/RECORD
