Metadata-Version: 2.1
Name: imgopt
Version: 0.3
Summary: Compress & Optimize Images
Home-page: UNKNOWN
Author: Vinay Chaudhary
License: UNKNOWN
Platform: UNKNOWN
Requires-Dist: requests
